proyectofinal/__init__.py
proyectofinal/perceptron.py
proyecto_BRADLEE_KEVIN_JUANPABLO-1.0.0.dist-info/LICENSE.txt
proyecto_BRADLEE_KEVIN_JUANPABLO-1.0.0.dist-info/METADATA
proyecto_BRADLEE_KEVIN_JUANPABLO-1.0.0.dist-info/WHEEL
proyecto_BRADLEE_KEVIN_JUANPABLO-1.0.0.dist-info/top_level.txt
proyecto_BRADLEE_KEVIN_JUANPABLO-1.0.0.dist-info/RECORD
