Metadata-Version: 2.1
Name: proyecto-BRADLEE-KEVIN-JUANPABLO
Version: 1.0.0
Summary: Usamos numpy para desarollar algunos problemas
Author: BRADLEE CASTRO-KEVIN ROA-JUAN BELEÑO
Classifier: Programming Language :: Python :: 3
Classifier: License :: OSI Approved :: MIT License
Classifier: Operating System :: OS Independent
Requires-Python: >=3.9
License-File: LICENSE.txt
Requires-Dist: numpy
